floof-0.1.11.dist-info/METADATA
floof-0.1.11.dist-info/WHEEL
floof/_matcher.py
floof/utils/types.py
floof/utils/utils.py
floof/utils/__init__.py
floof/__init__.py
floof/_rustyfloof.pyi
floof/_comparer.py
floof/_rustyfloof.cpython-38-i386-linux-gnu.so
floof-0.1.11.dist-info/RECORD
