Metadata-Version: 2.1
Name: floof
Version: 0.1.11
Classifier: Programming Language :: Rust
Classifier: Programming Language :: Python
Requires-Dist: pandas
Requires-Dist: scikit-learn
Requires-Dist: sparse_dot_topn
Summary: A library for fuzzymatching
Author: Cangyuan Li
License: MIT
Requires-Python: >=3.7
Project-URL: Source Code, https://github.com/cangyuanli/floof/
